django_bend/__init__.py
django_bend/convert.py
django_bend/parsing.py
django_bend/schema.py
django_bend/management/__init__.py
django_bend/management/commands/__init__.py
django_bend/management/commands/bend_data.py
django_bend-0.0.6.dist-info/DESCRIPTION.rst
django_bend-0.0.6.dist-info/METADATA
django_bend-0.0.6.dist-info/RECORD
django_bend-0.0.6.dist-info/WHEEL
django_bend-0.0.6.dist-info/metadata.json
django_bend-0.0.6.dist-info/top_level.txt
